clickable_textbox/__init__.py
clickable_textbox/example.py
clickable_textbox/frontend/build/asset-manifest.json
clickable_textbox/frontend/build/bootstrap.min.css
clickable_textbox/frontend/build/index.html
clickable_textbox/frontend/build/static/js/main.76b03de0.js
clickable_textbox/frontend/build/static/js/main.76b03de0.js.LICENSE.txt
clickable_textbox/frontend/build/static/js/main.76b03de0.js.map
clickable_textbox/frontend/build/static/js/main.780e20ca.js
clickable_textbox/frontend/build/static/js/main.780e20ca.js.LICENSE.txt
clickable_textbox/frontend/build/static/js/main.780e20ca.js.map
clickable_textbox/frontend/build/static/js/main.b2e05ea5.js
clickable_textbox/frontend/build/static/js/main.b2e05ea5.js.LICENSE.txt
clickable_textbox/frontend/build/static/js/main.b2e05ea5.js.map
streamlit_clickable_textbox-0.0.10.dist-info/LICENSE
streamlit_clickable_textbox-0.0.10.dist-info/METADATA
streamlit_clickable_textbox-0.0.10.dist-info/WHEEL
streamlit_clickable_textbox-0.0.10.dist-info/top_level.txt
streamlit_clickable_textbox-0.0.10.dist-info/RECORD
